muse_psfr/__init__.py
muse_psfr/cli.py
muse_psfr/coeffL0.fits
muse_psfr/psfrec.py
muse_psfr/test_psfrec.py
muse_psfr-1.0.dist-info/LICENSE
muse_psfr-1.0.dist-info/METADATA
muse_psfr-1.0.dist-info/WHEEL
muse_psfr-1.0.dist-info/entry_points.txt
muse_psfr-1.0.dist-info/top_level.txt
muse_psfr-1.0.dist-info/RECORD
